kilroyplot/__init__.py
kilroyplot/fonts.py
kilroyplot/plot.py
kilroyplot/resources/__init__.py
kilroyplot/utils.py
kilroyplot-0.2.5.dist-info/LICENSE
kilroyplot-0.2.5.dist-info/WHEEL
kilroyplot-0.2.5.dist-info/METADATA
kilroyplot-0.2.5.dist-info/RECORD
